[
    {
        "team": "Rays",
        "projectedW": 95.1,
        "projectedL": 66.9,
        "projectedRdiff": 182,
        "currentW": 23,
        "currentL": 6,
        "div%": 54.3,
        "wc%": 16.5,
        "post%": 70.8
    },
    {
        "team": "Braves",
        "projectedW": 92.7,
        "projectedL": 69.3,
        "projectedRdiff": 130,
        "currentW": 18,
        "currentL": 9,
        "div%": 65.2,
        "wc%": 12.7,
        "post%": 77.9
    },
    {
        "team": "Dodgers",
        "projectedW": 92.2,
        "projectedL": 69.8,
        "projectedRdiff": 145,
        "currentW": 16,
        "currentL": 13,
        "div%": 76.6,
        "wc%": 13.2,
        "post%": 89.8
    },
    {
        "team": "Astros",
        "projectedW": 90.5,
        "projectedL": 71.5,
        "projectedRdiff": 122,
        "currentW": 15,
        "currentL": 13,
        "div%": 52.0,
        "wc%": 38.0,
        "post%": 90.0
    },
    {
        "team": "Yankees",
        "projectedW": 88.6,
        "projectedL": 73.4,
        "projectedRdiff": 77,
        "currentW": 15,
        "currentL": 14,
        "div%": 18.6,
        "wc%": 49.1,
        "post%": 67.7
    },
    {
        "team": "Blue Jays",
        "projectedW": 87.8,
        "projectedL": 74.2,
        "projectedRdiff": 42,
        "currentW": 18,
        "currentL": 10,
        "div%": 16.2,
        "wc%": 47.5,
        "post%": 63.8
    },
    {
        "team": "Brewers",
        "projectedW": 87.2,
        "projectedL": 74.8,
        "projectedRdiff": 43,
        "currentW": 18,
        "currentL": 10,
        "div%": 38.4,
        "wc%": 32.8,
        "post%": 71.2
    },
    {
        "team": "Rangers",
        "projectedW": 86.7,
        "projectedL": 75.3,
        "projectedRdiff": 109,
        "currentW": 17,
        "currentL": 11,
        "div%": 29.6,
        "wc%": 40.5,
        "post%": 70.1
    },
    {
        "team": "Phillies",
        "projectedW": 85.7,
        "projectedL": 76.3,
        "projectedRdiff": 49,
        "currentW": 15,
        "currentL": 14,
        "div%": 19.9,
        "wc%": 40.3,
        "post%": 60.2
    },
    {
        "team": "Twins",
        "projectedW": 84.2,
        "projectedL": 77.8,
        "projectedRdiff": 33,
        "currentW": 17,
        "currentL": 12,
        "div%": 66.2,
        "wc%": 26.9,
        "post%": 93.0
    },
    {
        "team": "Cubs",
        "projectedW": 84.1,
        "projectedL": 77.9,
        "projectedRdiff": 67,
        "currentW": 14,
        "currentL": 13,
        "div%": 25.1,
        "wc%": 37.8,
        "post%": 62.9
    },
    {
        "team": "Orioles",
        "projectedW": 83.6,
        "projectedL": 78.4,
        "projectedRdiff": -4,
        "currentW": 19,
        "currentL": 9,
        "div%": 6.6,
        "wc%": 24.8,
        "post%": 31.3
    },
    {
        "team": "Pirates",
        "projectedW": 83.4,
        "projectedL": 78.6,
        "projectedRdiff": 19,
        "currentW": 20,
        "currentL": 9,
        "div%": 21.8,
        "wc%": 34.0,
        "post%": 55.8
    },
    {
        "team": "Mets",
        "projectedW": 82.0,
        "projectedL": 80.0,
        "projectedRdiff": -4,
        "currentW": 15,
        "currentL": 12,
        "div%": 9.9,
        "wc%": 28.0,
        "post%": 37.9
    },
    {
        "team": "Red Sox",
        "projectedW": 82.0,
        "projectedL": 80.0,
        "projectedRdiff": 24,
        "currentW": 15,
        "currentL": 14,
        "div%": 4.3,
        "wc%": 17.8,
        "post%": 22.0
    },
    {
        "team": "Mariners",
        "projectedW": 81.2,
        "projectedL": 80.8,
        "projectedRdiff": 22,
        "currentW": 12,
        "currentL": 16,
        "div%": 10.0,
        "wc%": 15.4,
        "post%": 25.4
    },
    {
        "team": "Padres",
        "projectedW": 81.2,
        "projectedL": 80.8,
        "projectedRdiff": -14,
        "currentW": 15,
        "currentL": 14,
        "div%": 9.8,
        "wc%": 23.8,
        "post%": 33.6
    },
    {
        "team": "Angels",
        "projectedW": 80.5,
        "projectedL": 81.5,
        "projectedRdiff": 4,
        "currentW": 15,
        "currentL": 14,
        "div%": 8.3,
        "wc%": 13.1,
        "post%": 21.4
    },
    {
        "team": "Diamondbacks",
        "projectedW": 80.5,
        "projectedL": 81.5,
        "projectedRdiff": -13,
        "currentW": 16,
        "currentL": 13,
        "div%": 8.4,
        "wc%": 21.2,
        "post%": 29.5
    },
    {
        "team": "Cardinals",
        "projectedW": 80.2,
        "projectedL": 81.8,
        "projectedRdiff": 17,
        "currentW": 10,
        "currentL": 19,
        "div%": 11.8,
        "wc%": 20.0,
        "post%": 31.8
    },
    {
        "team": "Marlins",
        "projectedW": 79.0,
        "projectedL": 83.0,
        "projectedRdiff": -73,
        "currentW": 16,
        "currentL": 13,
        "div%": 4.4,
        "wc%": 15.8,
        "post%": 20.2
    },
    {
        "team": "Giants",
        "projectedW": 77.6,
        "projectedL": 84.4,
        "projectedRdiff": -34,
        "currentW": 11,
        "currentL": 16,
        "div%": 4.8,
        "wc%": 12.5,
        "post%": 17.3
    },
    {
        "team": "Guardians",
        "projectedW": 77.1,
        "projectedL": 84.9,
        "projectedRdiff": -51,
        "currentW": 13,
        "currentL": 15,
        "div%": 20.7,
        "wc%": 6.5,
        "post%": 27.2
    },
    {
        "team": "Reds",
        "projectedW": 73.4,
        "projectedL": 88.6,
        "projectedRdiff": -70,
        "currentW": 12,
        "currentL": 16,
        "div%": 2.7,
        "wc%": 4.9,
        "post%": 7.6
    },
    {
        "team": "White Sox",
        "projectedW": 72.2,
        "projectedL": 89.8,
        "projectedRdiff": -88,
        "currentW": 8,
        "currentL": 21,
        "div%": 6.7,
        "wc%": 1.9,
        "post%": 8.6
    },
    {
        "team": "Tigers",
        "projectedW": 70.0,
        "projectedL": 92.0,
        "projectedRdiff": -112,
        "currentW": 10,
        "currentL": 17,
        "div%": 4.6,
        "wc%": 1.4,
        "post%": 6.0
    },
    {
        "team": "Nationals",
        "projectedW": 68.7,
        "projectedL": 93.3,
        "projectedRdiff": -112,
        "currentW": 10,
        "currentL": 17,
        "div%": 0.5,
        "wc%": 1.8,
        "post%": 2.3
    },
    {
        "team": "Rockies",
        "projectedW": 68.2,
        "projectedL": 93.8,
        "projectedRdiff": -128,
        "currentW": 9,
        "currentL": 20,
        "div%": 0.4,
        "wc%": 1.4,
        "post%": 1.8
    },
    {
        "team": "Royals",
        "projectedW": 66.7,
        "projectedL": 95.3,
        "projectedRdiff": -135,
        "currentW": 7,
        "currentL": 22,
        "div%": 1.8,
        "wc%": 0.5,
        "post%": 2.3
    },
    {
        "team": "Athletics",
        "projectedW": 60.6,
        "projectedL": 101.4,
        "projectedRdiff": -247,
        "currentW": 6,
        "currentL": 23,
        "div%": 0.1,
        "wc%": 0.1,
        "post%": 0.2
    }
]